TakeAiBLiP/AiBLiP.py
TakeAiBLiP/__init__.py
TakeAiBLiPModelManager-0.1.1.dist-info/DESCRIPTION.rst
TakeAiBLiPModelManager-0.1.1.dist-info/METADATA
TakeAiBLiPModelManager-0.1.1.dist-info/RECORD
TakeAiBLiPModelManager-0.1.1.dist-info/WHEEL
TakeAiBLiPModelManager-0.1.1.dist-info/metadata.json
TakeAiBLiPModelManager-0.1.1.dist-info/top_level.txt
test/__init__.py
