Metadata-Version: 2.0
Name: TakeAiBLiPModelManager
Version: 0.1.1
Summary: Package to automate the intents creation, examples addition, model training, publishin and analysis in the BLiP platform
Home-page: UNKNOWN
Author: Renan Santos
Author-email: renans@take.net
License: MIT License
Keywords: BLiP NLP Ai ML Test
Platform: UNKNOWN
